Trough-0.2.0.data/scripts/garbage_collector.py
Trough-0.2.0.data/scripts/reader.py
Trough-0.2.0.data/scripts/sync.py
Trough-0.2.0.data/scripts/udptee.py
Trough-0.2.0.data/scripts/writer.py
trough/__init__.py
trough/client.py
trough/db_api.py
trough/read.py
trough/settings.py
trough/sync.py
trough/write.py
trough/shell/__init__.py
trough/wsgi/__init__.py
trough/wsgi/segment_manager.py
Trough-0.2.0.dist-info/LICENSE
Trough-0.2.0.dist-info/METADATA
Trough-0.2.0.dist-info/WHEEL
Trough-0.2.0.dist-info/entry_points.txt
Trough-0.2.0.dist-info/top_level.txt
Trough-0.2.0.dist-info/RECORD
