Metadata-Version: 2.1
Name: Trough
Version: 0.2.0
Home-page: https://github.com/internetarchive/trough
Maintainer: James Kafader
Maintainer-email: jkafader@archive.org
License: BSD
Classifier: Development Status :: 4 - Beta
Classifier: Topic :: Database :: Database Engines/Servers
Classifier: License :: OSI Approved :: BSD License
License-File: LICENSE
Requires-Dist: protobuf (<4,>=3.7.1)
Requires-Dist: PyYAML (>=5.1)
Requires-Dist: requests (>=2.21.0)
Requires-Dist: six (>=1.10.0)
Requires-Dist: snakebite-py3 (>=3.0)
Requires-Dist: ujson-ia (>=2.1.1)
Requires-Dist: sqlparse (>=0.2.2)
Requires-Dist: uWSGI (>=2.0.15)
Requires-Dist: doublethink (>=0.2.0)
Requires-Dist: uhashring (<1.0,>=0.7)
Requires-Dist: flask (<2,>=1.0.2)
Requires-Dist: sqlitebck (>=1.4)
Requires-Dist: hdfs3 (>=0.2.0)
Requires-Dist: aiodns (>=1.2.0)
Requires-Dist: aiohttp (<=3.0.0b0,>=2.3.10)
Requires-Dist: async-timeout (<3.0.0)
